suncal/__init__.py
suncal/spa.py
suncal/suncal.py
suncal/sunstats.py
solarcal-1.1.3.dist-info/LICENSE
solarcal-1.1.3.dist-info/METADATA
solarcal-1.1.3.dist-info/WHEEL
solarcal-1.1.3.dist-info/top_level.txt
solarcal-1.1.3.dist-info/RECORD
