Metadata-Version: 2.1
Name: solarcal
Version: 1.1.3
Summary: Ground radar monitoring of calibration using the Sun as reference.
Home-page: https://github.com/vlouf/suncal
Author: Valentin Louf
Author-email: valentin.louf@bom.gov.au
Project-URL: Bug Reports, https://github.com/vlouf/suncal/issues
Project-URL: Source, https://github.com/vlouf/suncal/
Keywords: radar weather meteorology calibration
Classifier: Development Status :: 5 - Production/Stable
Classifier: Intended Audience :: Science/Research
Classifier: Topic :: Scientific/Engineering :: Atmospheric Science
Classifier: License :: OSI Approved :: MIT License
Classifier: Programming Language :: Python :: 3.8
Classifier: Programming Language :: Python :: 3.9
Classifier: Programming Language :: Python :: 3.10
Classifier: Programming Language :: Python :: 3.11
Classifier: Programming Language :: Python :: 3.12
License-File: LICENSE
Requires-Dist: numpy
Requires-Dist: pyodim
Requires-Dist: pandas
Requires-Dist: h5py
Requires-Dist: scipy
Requires-Dist: scikit-learn
